kalorda/__init__.py
kalorda/constant.py
kalorda/main.py
kalorda/package.py
kalorda/config/__init__.py
kalorda/config/base.py
kalorda/config/development.py
kalorda/config/production.py
kalorda/core/__init__.py
kalorda/core/dataset_preocr.py
kalorda/core/finetune_trainer.py
kalorda/core/gpu_task_monitor.py
kalorda/core/modeltest_runner.py
kalorda/core/package_installer.py
kalorda/core/sft_data_builder.py
kalorda/core/sft_data_prompt.py
kalorda/core/system_env_info.py
kalorda/database/__init__.py
kalorda/database/database.py
kalorda/locales/messages.pot
kalorda/locales/en_US/LC_MESSAGES/messages.mo
kalorda/locales/en_US/LC_MESSAGES/messages.po
kalorda/locales/zh_CN/LC_MESSAGES/messages.mo
kalorda/locales/zh_CN/LC_MESSAGES/messages.po
kalorda/models/__init__.py
kalorda/models/auth.py
kalorda/models/dataset.py
kalorda/models/finetune.py
kalorda/models/modeltest.py
kalorda/models/system.py
kalorda/models/user.py
kalorda/routes/__init__.py
kalorda/routes/admin.py
kalorda/routes/auth.py
kalorda/routes/dataset.py
kalorda/routes/finetune.py
kalorda/routes/home.py
kalorda/routes/modeltest.py
kalorda/routes/stream.py
kalorda/routes/system.py
kalorda/utils/__init__.py
kalorda/utils/aes_crypto.py
kalorda/utils/api_response.py
kalorda/utils/cache.py
kalorda/utils/data_verify.py
kalorda/utils/email_send.py
kalorda/utils/exception_handler.py
kalorda/utils/i18n.py
kalorda/utils/logger.py
kalorda/utils/security.py
kalorda/utils/sse_stream.py
kalorda/utils/upload_file.py
kalorda/utils/zmq_pubsub.py
kalorda/vllm_infer/__init__.py
kalorda/vllm_infer/vllm_engine.py
kalorda/vllm_infer/vllm_plugins.py
kalorda/vllm_infer/deepseek_ocr/__init__.py
kalorda/vllm_infer/deepseek_ocr/config.py
kalorda/vllm_infer/deepseek_ocr/deepseek_ocr.py
kalorda/vllm_infer/deepseek_ocr/modeling_plugin.py
kalorda/vllm_infer/deepseek_ocr/vlm_offline_infer.py
kalorda/vllm_infer/deepseek_ocr/vlm_offline_infer_v10_1.py
kalorda/vllm_infer/deepseek_ocr/vlm_offline_infer_v11_2.py
kalorda-0.1.6.dist-info/licenses/LICENSE
kalorda-0.1.6.dist-info/METADATA
kalorda-0.1.6.dist-info/WHEEL
kalorda-0.1.6.dist-info/entry_points.txt
kalorda-0.1.6.dist-info/top_level.txt
kalorda-0.1.6.dist-info/RECORD
