Metadata-Version: 2.4
Name: kalorda
Version: 0.1.6
Summary: integrated fine-tuning platform for lightweight vlmOCR models
Author-email: kalorda <postmaster@vlmocr.com>
License-Expression: Apache-2.0
Project-URL: Homepage, https://kalorda.vlmocr.com
Project-URL: Repository, https://github.com/vlmOCR/Kalorda.git
Project-URL: Bug Tracker, https://github.com/vlmOCR/Kalorda/issues
Keywords: vlm ocr model,vlm ocr model label,vlm ocr model fine-tune,vlm ocr model test,vllm,ms-swift
Classifier: Programming Language :: Python :: 3
Requires-Python: >=3.10
License-File: LICENSE
Requires-Dist: types-cachetools
Requires-Dist: bcrypt==4.0.1
Requires-Dist: passlib
Requires-Dist: python-jose
Requires-Dist: natsort
Requires-Dist: peewee
Requires-Dist: verovio
Requires-Dist: pdf2image
Requires-Dist: Spire.Pdf.Free
Requires-Dist: poppler-utils
Requires-Dist: pysqlite3-binary
Requires-Dist: pymysql
Requires-Dist: pyzmq
Requires-Dist: sse-starlette
Requires-Dist: qwen_vl_utils
Requires-Dist: easydict
Requires-Dist: peft==0.17.1
Requires-Dist: torch==2.9.0
Requires-Dist: vllm
Requires-Dist: ms-swift
Requires-Dist: babel
Provides-Extra: dev
Requires-Dist: pre-commit>=3.6.0; extra == "dev"
Requires-Dist: black>=24.8.0; extra == "dev"
Requires-Dist: isort>=5.13.2; extra == "dev"
Requires-Dist: flake8>=7.1.0; extra == "dev"
Requires-Dist: mypy>=1.8.0; extra == "dev"
Requires-Dist: flake8-docstrings>=1.7.0; extra == "dev"
Requires-Dist: pydocstyle>=6.3.0; extra == "dev"
Dynamic: license-file
